MANIFEST.in
README.rst
setup.py
pmt/__init__.py
pmt/pmt.py
pmt.egg-info/PKG-INFO
pmt.egg-info/SOURCES.txt
pmt.egg-info/dependency_links.txt
pmt.egg-info/top_level.txt